{
  "start_date": "2025-01-02",
  "end_date": "2025-06-30",
  "n_periods": 122,
  "n_trades": 60,
  "total_return": -0.3708643561725178,
  "cagr": -0.7552897344727749,
  "avg_trade_return": 0.19648249501443377,
  "median_trade_return": -3.540579374476077,
  "sharpe": -0.6910070604187515,
  "max_dd": -7.794093367703901,
  "calmar": -0.09690539987658363,
  "volatility": 7.905308444025493,
  "win_rate_pct": 38.333333333333336,
  "profit_factor": 1.0595241591871623,
  "avg_win": 9.123571358381453,
  "avg_loss": -5.3527889605920915,
  "benchmark_return": 6.311687601128191,
  "excess_return": -6.682551957300708,
  "information_ratio": -0.7304113061990152,
  "p_value": 0.6136957394416913,
  "ci_lower": -0.003402614446504221,
  "ci_upper": 0.001735122740372984,
  "config": {
    "start_date": "2025-01-01",
    "end_date": "2025-06-30",
    "rebalance_freq": "monthly",
    "top_k": 10,
    "holding_days": 20,
    "universe_size": 50,
    "initial_capital": 100000,
    "enable_ml": true,
    "enable_fundamentals": true,
    "enable_patterns": true
  }
}