{
  "start_date": "2025-06-02",
  "end_date": "2026-03-13",
  "n_periods": 197,
  "n_trades": 100,
  "total_return": 10.513472337790786,
  "cagr": 13.71976500234313,
  "avg_trade_return": 1.7533873496129564,
  "median_trade_return": 0.22331229304765055,
  "sharpe": 0.8205768009450355,
  "max_dd": -5.642075111602013,
  "calmar": 2.431687762208387,
  "volatility": 10.206274545312695,
  "win_rate_pct": 51.0,
  "profit_factor": 1.6371920588355668,
  "avg_win": 8.833584495932117,
  "avg_loss": -5.615797435331476,
  "benchmark_return": 12.712400638231758,
  "excess_return": -2.198928300440972,
  "information_ratio": -0.27389507910823685,
  "p_value": 0.8093805527031784,
  "ci_lower": -0.0009482528607889107,
  "ci_upper": 0.0007319952887702808,
  "config": {
    "start_date": "2025-06-01",
    "end_date": "2026-03-13",
    "rebalance_freq": "monthly",
    "top_k": 10,
    "holding_days": 20,
    "universe_size": 200,
    "initial_capital": 100000,
    "enable_ml": true,
    "enable_fundamentals": true,
    "enable_patterns": true
  }
}